AUTHORS.rst
CONTRIBUTING.rst
HISTORY.rst
LICENSE.rst
MANIFEST.in
README.rst
requirements-dev.txt
requirements.txt
setup.py
djangorestframework_bulk.egg-info/PKG-INFO
djangorestframework_bulk.egg-info/SOURCES.txt
djangorestframework_bulk.egg-info/dependency_links.txt
djangorestframework_bulk.egg-info/requires.txt
djangorestframework_bulk.egg-info/top_level.txt
rest_framework_bulk/__init__.py
rest_framework_bulk/generics.py
rest_framework_bulk/mixins.py
rest_framework_bulk/models.py
rest_framework_bulk/routes.py
rest_framework_bulk/serializers.py
rest_framework_bulk/drf2/__init__.py
rest_framework_bulk/drf2/mixins.py
rest_framework_bulk/drf2/serializers.py
rest_framework_bulk/drf3/__init__.py
rest_framework_bulk/drf3/mixins.py
rest_framework_bulk/drf3/serializers.py
rest_framework_bulk/tests/__init__.py
rest_framework_bulk/tests/test_generics.py
rest_framework_bulk/tests/simple_app/__init__.py
rest_framework_bulk/tests/simple_app/models.py
rest_framework_bulk/tests/simple_app/serializers.py
rest_framework_bulk/tests/simple_app/urls.py
rest_framework_bulk/tests/simple_app/views.py
tests/manage.py
tests/runtests.sh
tests/settings.py