Metadata-Version: 1.1
Name: djangorestframework-bulk
Version: 0.2
Summary: Django REST Framework bulk CRUD view mixins
Home-page: https://github.com/miki725/django-rest-framework-bulk
Author: Miroslav Shubernetskiy
Author-email: miroslav@miki725.com
License: MIT
Keywords: django
Platform: UNKNOWN
Classifier: Development Status :: 3 - Alpha
Classifier: Framework :: Django
Classifier: Intended Audience :: Developers
Classifier: Operating System :: OS Independent
Classifier: Programming Language :: Python
Classifier: Programming Language :: Python :: 3
Classifier: Topic :: Utilities
Classifier: Topic :: Internet :: WWW/HTTP
Classifier: License :: OSI Approved :: MIT License
